.rtfd-requirements.txt
CHANGELOG.md
CONTRIBUTING.md
LICENSE.txt
MANIFEST.in
PULL_REQUEST_TEMPLATE.md
README.md
renovate.json
requirements.txt
setup.py
fair_solaris.egg-info/PKG-INFO
fair_solaris.egg-info/SOURCES.txt
fair_solaris.egg-info/dependency_links.txt
fair_solaris.egg-info/entry_points.txt
fair_solaris.egg-info/not-zip-safe
fair_solaris.egg-info/requires.txt
fair_solaris.egg-info/top_level.txt
solaris/__init__.py
solaris/bin/__init__.py
solaris/bin/geotransform_footprints.py
solaris/bin/make_graphs.py
solaris/bin/make_masks.py
solaris/bin/mask_to_polygons.py
solaris/bin/solaris_run_ml.py
solaris/bin/spacenet_eval.py
solaris/data/SN2_sample_iou_by_building.csv
solaris/data/SN2_sample_preds.csv
solaris/data/SN2_sample_truth.csv
solaris/data/SN2_test_results.csv
solaris/data/SN2_test_results_full.csv
solaris/data/__init__.py
solaris/data/aff_gdf_result.csv
solaris/data/coco.py
solaris/data/coco_sample_1.json
solaris/data/coco_sample_2.json
solaris/data/coco_sample_3.json
solaris/data/competition_test_results.csv
solaris/data/competition_test_results_full.csv
solaris/data/empty.geojson
solaris/data/gdf_from_mask_1.geojson
solaris/data/gdf_from_mask_2.geojson
solaris/data/geotiff_custom_proj_labels.geojson
solaris/data/geotiff_labels.geojson
solaris/data/gj_to_px_result.geojson
solaris/data/gt.geojson
solaris/data/gt_epsg4326.json
solaris/data/inference_tiler_test_output.npy
solaris/data/nebraska_landsat5_with_nodata_wgs84.tif
solaris/data/nebraska_wgs84_with_nodata_labels.geojson
solaris/data/overlap_test.geojson
solaris/data/pred.geojson
solaris/data/restrict_aoi_test.geojson
solaris/data/road_mask_input.tif
solaris/data/sample.csv
solaris/data/sample.geojson
solaris/data/sample_b_from_df2px.tif
solaris/data/sample_b_mask_inner.tif
solaris/data/sample_b_mask_outer.tif
solaris/data/sample_b_mask_outer_10.tif
solaris/data/sample_c_from_df2px.tif
solaris/data/sample_c_mask.tif
solaris/data/sample_fbc_from_df2px.tif
solaris/data/sample_fp_from_df2px.tif
solaris/data/sample_fp_mask.tif
solaris/data/sample_fp_mask_from_geojson.tif
solaris/data/sample_geotiff.tif
solaris/data/sample_geotiff.tif.txt
solaris/data/sample_geotiff_custom_proj.tif
solaris/data/sample_graph.pkl
solaris/data/sample_inst_mask.tif
